odoo/addons/stock_realign_move_and_quants/README.rst
odoo/addons/stock_realign_move_and_quants/__init__.py
odoo/addons/stock_realign_move_and_quants/__manifest__.py
odoo/addons/stock_realign_move_and_quants/i18n/stock_realign_move_and_quants.pot
odoo/addons/stock_realign_move_and_quants/models/__init__.py
odoo/addons/stock_realign_move_and_quants/models/stock_quant.py
odoo/addons/stock_realign_move_and_quants/readme/CONTRIBUTORS.rst
odoo/addons/stock_realign_move_and_quants/readme/DESCRIPTION.rst
odoo/addons/stock_realign_move_and_quants/readme/ROADMAP.rst
odoo/addons/stock_realign_move_and_quants/readme/USAGE.rst
odoo/addons/stock_realign_move_and_quants/security/ir.model.access.csv
odoo/addons/stock_realign_move_and_quants/static/description/icon.png
odoo/addons/stock_realign_move_and_quants/static/description/index.html
odoo/addons/stock_realign_move_and_quants/wizard/__init__.py
odoo/addons/stock_realign_move_and_quants/wizard/align_move_quant_wizard.py
odoo/addons/stock_realign_move_and_quants/wizard/align_move_quant_wizard_views.xml
odoo12_addon_stock_realign_move_and_quants-12.0.1.0.1.dist-info/METADATA
odoo12_addon_stock_realign_move_and_quants-12.0.1.0.1.dist-info/WHEEL
odoo12_addon_stock_realign_move_and_quants-12.0.1.0.1.dist-info/top_level.txt
odoo12_addon_stock_realign_move_and_quants-12.0.1.0.1.dist-info/RECORD
