Metadata-Version: 2.1
Name: odoo12-addon-stock-realign-move-and-quants
Version: 12.0.1.0.1
Summary: Align stock move lines and stock quants. This modules fixes the symptoms and not the root cause.
Home-page: https://github.com/OCA/stock-logistics-warehouse
Author: Camptocamp,Coop IT Easy SCRLfs,Odoo Community Association (OCA)
Author-email: support@odoo-community.org
License: AGPL-3
Platform: UNKNOWN
Classifier: Programming Language :: Python
Classifier: Framework :: Odoo
Classifier: Framework :: Odoo :: 12.0
Classifier: License :: OSI Approved :: GNU Affero General Public License v3
Requires-Python: >=3.5
Requires-Dist: odoo (<12.1dev,>=12.0a)
